owasp_jenkins/__init__.py
owasp_jenkins/log/__init__.py
owasp_jenkins/log/build_logstash_formatter.py
owasp_jenkins/log/setup_logging.py
owasp_jenkins-1.0.2.dist-info/LICENSE
owasp_jenkins-1.0.2.dist-info/METADATA
owasp_jenkins-1.0.2.dist-info/WHEEL
owasp_jenkins-1.0.2.dist-info/top_level.txt
owasp_jenkins-1.0.2.dist-info/RECORD
