Metadata-Version: 2.1
Name: owasp-jenkins
Version: 1.0.2
Summary: Automate your OWASP analysis within a Jenkins docker container that is preconfigured to use Ansible to scan and report on potential python security issues before they are deployed to production.
Home-page: https://github.com/jay-johnson/owasp-jenkins
Author: Jay Johnson
Author-email: jay.p.h.johnson@gmail.com
License: UNKNOWN
Platform: UNKNOWN
Classifier: Development Status :: 5 - Production/Stable
Classifier: Intended Audience :: Developers
Classifier: License :: OSI Approved :: Apache Software License
Classifier: Operating System :: OS Independent
Classifier: Programming Language :: Python :: 2.7
Classifier: Programming Language :: Python :: 3.5
Classifier: Programming Language :: Python :: 3.6
Classifier: Programming Language :: Python :: Implementation :: PyPy
Classifier: Topic :: Software Development :: Libraries :: Python Modules
Requires-Dist: ansible (>=2.4)
Requires-Dist: bandit
Requires-Dist: coverage
Requires-Dist: docker-compose
Requires-Dist: flake8
Requires-Dist: future
Requires-Dist: mock
Requires-Dist: paramiko
Requires-Dist: pep8
Requires-Dist: pycurl
Requires-Dist: pylint
Requires-Dist: python-owasp-zap-v2.4
Requires-Dist: safety
Requires-Dist: unittest2
